django_dicom/__init__.py
django_dicom/admin.py
django_dicom/apps.py
django_dicom/forms.py
django_dicom/signals.py
django_dicom/urls.py
django_dicom/utils.py
django_dicom/views.py
django_dicom/data_import/__init__.py
django_dicom/data_import/import_image.py
django_dicom/data_import/local_import.py
django_dicom/exploration/__init__.py
django_dicom/filters/__init__.py
django_dicom/filters/image_filter.py
django_dicom/filters/patient_filter.py
django_dicom/filters/series_filter.py
django_dicom/filters/study_filter.py
django_dicom/migrations/__init__.py
django_dicom/models/__init__.py
django_dicom/models/choice_enum.py
django_dicom/models/choices.py
django_dicom/models/dicom_entity.py
django_dicom/models/fields.py
django_dicom/models/help_text.py
django_dicom/models/image.py
django_dicom/models/instance.py
django_dicom/models/nifti.py
django_dicom/models/patient.py
django_dicom/models/series.py
django_dicom/models/study.py
django_dicom/models/validators.py
django_dicom/models/managers/__init__.py
django_dicom/models/managers/series.py
django_dicom/reader/__init__.py
django_dicom/reader/header_information.py
django_dicom/reader/parser.py
django_dicom/reader/value_representation.py
django_dicom/reader/code_strings/__init__.py
django_dicom/reader/code_strings/modality.py
django_dicom/reader/code_strings/patient_position.py
django_dicom/reader/code_strings/scanning_sequence.py
django_dicom/reader/code_strings/sequence_variant.py
django_dicom/reader/code_strings/sex.py
django_dicom/serializers/__init__.py
django_dicom/serializers/image_serializer.py
django_dicom/serializers/patient_serializer.py
django_dicom/serializers/series_serializer.py
django_dicom/serializers/study_serializer.py
django_dicom/templates/dicom/instances/instance_detail.html
django_dicom/templates/dicom/instances/instance_list.html
django_dicom/templates/dicom/instances/instances_create.html
django_dicom/templates/dicom/patients/patient_detail.html
django_dicom/templates/dicom/patients/patient_list.html
django_dicom-0.0.4.dist-info/LICENSE
django_dicom-0.0.4.dist-info/METADATA
django_dicom-0.0.4.dist-info/WHEEL
django_dicom-0.0.4.dist-info/top_level.txt
django_dicom-0.0.4.dist-info/RECORD
